pylearn/__init__.py
pylearn/model_utils.py
pylearn/classification/__init__.py
pylearn/classification/gaussian_naive_bayes.py
pylearn/classification/multinomial_naive_bayes.py
pylearn/clustering/__init__.py
pylearn/clustering/clustering.py
pylearn/clustering/gaussian_mixture_model.py
pylearn/clustering/k_means.py
pylearn/clustering/k_medoids.py
pylearn/neural_network/__init__.py
pylearn/neural_network/activation.py
pylearn/neural_network/activation_functions.py
pylearn/neural_network/dense_layer.py
pylearn/neural_network/layer.py
pylearn/neural_network/loss_functions.py
pylearn/neural_network/network.py
tests/__init__.py
tests/test_clustering.py
tests/test_gaussian_mixture_model.py
tests/test_gaussian_naive_bayes.py
tests/test_k_means.py
tests/test_k_medoids.py
tests/test_model_utils.py
tests/test_network.py
pylearn_ml-1.2.0.dist-info/LICENSE
pylearn_ml-1.2.0.dist-info/METADATA
pylearn_ml-1.2.0.dist-info/WHEEL
pylearn_ml-1.2.0.dist-info/top_level.txt
pylearn_ml-1.2.0.dist-info/RECORD
