Metadata-Version: 2.1
Name: pylearn-ml
Version: 1.2.0
Home-page: https://github.com/JanSkn/machine-learning-library
Author: Jan Skowron
License-File: LICENSE
Requires-Dist: numpy
Requires-Dist: pandas
Requires-Dist: dill
Requires-Dist: matplotlib
Requires-Dist: pytest
Requires-Dist: sphinx
Requires-Dist: sphinx-theme-pd
